{
  "id": "Either.getRight",
  "name": "getRight",
  "module": "Either",
  "package": "effect",
  "signature": "<A, E>(self: Either<A, E>) => Option<A>",
  "description": "Converts a `Either` to an `Option` discarding the `Left`.",
  "documentation": "Converts a `Either` to an `Option` discarding the `Left`.",
  "examples": [
    {
      "code": "import * as assert from \"node:assert\"\nimport { Either, Option } from \"effect\"\n\nassert.deepStrictEqual(Either.getRight(Either.right('ok')), Option.some('ok'))\nassert.deepStrictEqual(Either.getRight(Either.left('err')), Option.none())"
    }
  ],
  "tags": [
    "getters"
  ],
  "since": "2.0.0",
  "sourceFile": "/Users/benjacobson/conductor/workspaces/hoogle-effect/san-juan-v1/packages/api/node_modules/effect/dist/dts/Either.d.ts",
  "sourceLine": 296,
  "githubUrl": "https://github.com/Effect-TS/effect/blob/main/packages/effect/src/Either.ts#L296"
}