{
  "id": "Exit.isFailure",
  "name": "isFailure",
  "module": "Exit",
  "package": "effect",
  "signature": "<A, E>(self: Exit<A, E>) => self is Failure<A, E>",
  "description": "Returns `true` if the specified `Exit` is a `Failure`, `false` otherwise.",
  "documentation": "Returns `true` if the specified `Exit` is a `Failure`, `false` otherwise.",
  "examples": [],
  "tags": [
    "refinements"
  ],
  "since": "2.0.0",
  "sourceFile": "/Users/benjacobson/conductor/workspaces/hoogle-effect/san-juan-v1/packages/api/node_modules/effect/dist/dts/Exit.d.ts",
  "sourceLine": 84,
  "githubUrl": "https://github.com/Effect-TS/effect/blob/main/packages/effect/src/Exit.ts#L84"
}