{
  "id": "HttpMultiplex.add",
  "name": "add",
  "module": "HttpMultiplex",
  "package": "@effect/platform",
  "signature": "{ <E2, R2, E3, R3>(predicate: (request: HttpServerRequest) => Effect<boolean, E2, R2>, app: Default<E3, R3>): <E, R>(self: HttpMultiplex<E, R>) => HttpMultiplex<E2 | E3 | E, R2 | R3 | R>; <E, R, E2, R2, E3, R3>(self: HttpMultiplex<E, R>, predicate: (request: HttpServerRequest) => Effect<boolean, E2, R2>, app: Default<E3, R3>): HttpMultiplex<E | E2 | E3, R | R2 | R3>; }",
  "description": "",
  "documentation": "",
  "examples": [],
  "tags": [
    "combinators"
  ],
  "since": "1.0.0",
  "sourceFile": "/Users/benjacobson/conductor/workspaces/hoogle-effect/san-juan-v1/packages/api/node_modules/@effect/platform/dist/dts/HttpMultiplex.d.ts",
  "sourceLine": 47,
  "githubUrl": "https://github.com/Effect-TS/effect/blob/main/packages/platform/src/HttpMultiplex.ts#L47"
}