{
  "id": "HttpClientRequest.bodyText",
  "name": "bodyText",
  "module": "HttpClientRequest",
  "package": "@effect/platform",
  "signature": "{ (body: string, contentType?: string): (self: HttpClientRequest) => HttpClientRequest; (self: HttpClientRequest, body: string, contentType?: string): HttpClientRequest; }",
  "description": "",
  "documentation": "",
  "examples": [],
  "tags": [
    "combinators"
  ],
  "since": "1.0.0",
  "sourceFile": "/Users/benjacobson/conductor/workspaces/hoogle-effect/san-juan-v1/packages/api/node_modules/@effect/platform/dist/dts/HttpClientRequest.d.ts",
  "sourceLine": 419,
  "githubUrl": "https://github.com/Effect-TS/effect/blob/main/packages/platform/src/HttpClientRequest.ts#L419"
}