{
  "id": "Result.match",
  "name": "match",
  "module": "Result",
  "package": "@effect-atom/atom",
  "signature": "{ <A, E, X, Y, Z>(options: { readonly onInitial: (_: Initial<A, E>) => X; readonly onFailure: (_: Failure<A, E>) => Y; readonly onSuccess: (_: Success<A, E>) => Z; }): (self: Result<A, E>) => X | Y | Z; <A, E, X, Y, Z>(self: Result<A, E>, options: { readonly onInitial: (_: Initial<A, E>) => X; readonly onFailure: (_: Failure<A, E>) => Y; readonly onSuccess: (_: Success<A, E>) => Z; }): X | Y | Z; }",
  "description": "",
  "documentation": "",
  "examples": [],
  "tags": [
    "combinators"
  ],
  "since": "1.0.0",
  "sourceFile": "/Users/benjacobson/conductor/workspaces/hoogle-effect/san-juan-v1/packages/api/node_modules/@effect-atom/atom/dist/dts/Result.d.ts",
  "sourceLine": 246,
  "githubUrl": "https://github.com/tim-smart/effect-atom/blob/main/packages/atom/src/Result.ts#L246"
}