{
  "id": "Stream.runDrain",
  "name": "runDrain",
  "module": "Stream",
  "package": "effect",
  "signature": "<A, E, R>(self: Stream<A, E, R>) => Effect<void, E, R>",
  "description": "Runs the stream only for its effects. The emitted elements are discarded.",
  "documentation": "Runs the stream only for its effects. The emitted elements are discarded.",
  "examples": [],
  "tags": [
    "destructors"
  ],
  "since": "2.0.0",
  "sourceFile": "/Users/benjacobson/conductor/workspaces/hoogle-effect/san-juan-v1/packages/api/node_modules/effect/dist/dts/Stream.d.ts",
  "sourceLine": 7008,
  "githubUrl": "https://github.com/Effect-TS/effect/blob/main/packages/effect/src/Stream.ts#L7008"
}