{
  "id": "Stream.runHead",
  "name": "runHead",
  "module": "Stream",
  "package": "effect",
  "signature": "<A, E, R>(self: Stream<A, E, R>) => Effect<Option<A>, E, R>",
  "description": "Runs the stream to completion and yields the first value emitted by it,\ndiscarding the rest of the elements.",
  "documentation": "Runs the stream to completion and yields the first value emitted by it,\ndiscarding the rest of the elements.",
  "examples": [],
  "tags": [
    "destructors"
  ],
  "since": "2.0.0",
  "sourceFile": "/Users/benjacobson/conductor/workspaces/hoogle-effect/san-juan-v1/packages/api/node_modules/effect/dist/dts/Stream.d.ts",
  "sourceLine": 7369,
  "githubUrl": "https://github.com/Effect-TS/effect/blob/main/packages/effect/src/Stream.ts#L7369"
}