{
  "id": "Stream.orDie",
  "name": "orDie",
  "module": "Stream",
  "package": "effect",
  "signature": "<A, E, R>(self: Stream<A, E, R>) => Stream<A, never, R>",
  "description": "Translates any failure into a stream termination, making the stream\ninfallible and all failures unchecked.",
  "documentation": "Translates any failure into a stream termination, making the stream\ninfallible and all failures unchecked.",
  "examples": [],
  "tags": [
    "error handling"
  ],
  "since": "2.0.0",
  "sourceFile": "/Users/benjacobson/conductor/workspaces/hoogle-effect/san-juan-v1/packages/api/node_modules/effect/dist/dts/Stream.d.ts",
  "sourceLine": 5445,
  "githubUrl": "https://github.com/Effect-TS/effect/blob/main/packages/effect/src/Stream.ts#L5445"
}